kafkaproxy/__init__.py
kafkaproxy/consumer.py
kafkaproxy/models.py
kafkaproxy/producer.py
kafkaproxy/protocols.py
kafkaproxy-0.0.1.dist-info/LICENSE
kafkaproxy-0.0.1.dist-info/METADATA
kafkaproxy-0.0.1.dist-info/WHEEL
kafkaproxy-0.0.1.dist-info/top_level.txt
kafkaproxy-0.0.1.dist-info/RECORD
