Metadata-Version: 2.1
Name: kafkaproxy
Version: 0.0.1
Summary: kafka consumer and producer proxy
Author: hsz
Author-email: hsz1273327@gmail.com
License: MIT License
Keywords: kafka,proxy,consumer,producer
Classifier: License :: OSI Approved :: MIT License
Classifier: Programming Language :: Python :: 3.8
Classifier: Programming Language :: Python :: 3.9
Classifier: Programming Language :: Python :: 3.10
License-File: LICENSE
Requires-Dist: pyproxypattern (>=0.0.1)
Provides-Extra: aio
Requires-Dist: aiokafka (>=0.8.0) ; extra == 'aio'
Provides-Extra: confluent
Requires-Dist: confluent-kafka (>=2.0.0) ; extra == 'confluent'
Provides-Extra: kafka
Requires-Dist: kafka-python (>=2.0.0) ; extra == 'kafka'
